cimcon/__init__.py
cimcon/cimconpy.py
cimcon-1.0.3.dist-info/METADATA
cimcon-1.0.3.dist-info/WHEEL
cimcon-1.0.3.dist-info/licenses/LICENSE.md
cimcon-1.0.3.dist-info/RECORD
