Metadata-Version: 2.3
Name: cimcon
Version: 1.0.3
Summary: CIMCON python package for model evaluation
Author: CIMCON
License-File: LICENSE.md
Classifier: Operating System :: OS Independent
Classifier: Programming Language :: Python :: 3
Requires-Dist: fairlearn==0.10.0
Requires-Dist: mapie==0.8.3
Requires-Dist: matplotlib==3.8.0
Requires-Dist: numpy==1.26.4
Requires-Dist: openpyxl==3.1.2
Requires-Dist: pandas==2.1.4
Requires-Dist: pillow==10.2.0
Requires-Dist: scikit-learn==1.2.2
Requires-Dist: scipy==1.11.4
Requires-Dist: seaborn==0.13.2
Requires-Dist: shap<=0.44.1,>=0.42.1
